GeneOpt/CachePath.py
GeneOpt/GeneticAlgorithm.py
GeneOpt/GeneticAlgorithmCache.py
GeneOpt/GeneticAlgorithmCacheType.py
GeneOpt/GeneticAlgorithmComparisonType.py
GeneOpt/Util.py
GeneOpt/__init__.py
GeneOpt-1.0.10.dist-info/LICENSE
GeneOpt-1.0.10.dist-info/METADATA
GeneOpt-1.0.10.dist-info/WHEEL
GeneOpt-1.0.10.dist-info/top_level.txt
GeneOpt-1.0.10.dist-info/RECORD
