Metadata-Version: 2.1
Name: GeneOpt
Version: 1.0.10
Summary: A library for genetic optimization
Home-page: https://github.com/erfanmhat/GeneOpt
Author: Erfan Mahdavi Athar
Author-email: erfan.mh.at@gmail.com
Classifier: Programming Language :: Python :: 3
Classifier: License :: OSI Approved :: MIT License
Classifier: Operating System :: OS Independent
Requires-Python: >=3.6
License-File: LICENSE
Requires-Dist: numpy >=1.21.0
Requires-Dist: pandas >=1.3.0
Requires-Dist: matplotlib >=3.4.0
Requires-Dist: seaborn >=0.11.0
Requires-Dist: catboost >=1.0.0
Requires-Dist: scikit-learn >=0.24.0
